pytest_coverage_impact/__init__.py
pytest_coverage_impact/constants.py
pytest_coverage_impact/plugin.py
pytest_coverage_impact/core/config.py
pytest_coverage_impact/core/impact_calculator.py
pytest_coverage_impact/core/prioritizer.py
pytest_coverage_impact/di/container.py
pytest_coverage_impact/domain/protocols.py
pytest_coverage_impact/gateways/call_graph.py
pytest_coverage_impact/gateways/progress.py
pytest_coverage_impact/gateways/reporters.py
pytest_coverage_impact/gateways/utils.py
pytest_coverage_impact/interface/telemetry.py
pytest_coverage_impact/logic/analyzer.py
pytest_coverage_impact/ml/__init__.py
pytest_coverage_impact/ml/complexity_estimator.py
pytest_coverage_impact/ml/complexity_model.py
pytest_coverage_impact/ml/feature_extractor.py
pytest_coverage_impact/ml/gateway.py
pytest_coverage_impact/ml/test_analyzer.py
pytest_coverage_impact/ml/training_data_collector.py
pytest_coverage_impact/ml/versioning.py
pytest_coverage_impact/ml/models/complexity_model_v1.0.pkl
pytest_coverage_impact-1.5.0.dist-info/licenses/LICENSE
pytest_coverage_impact-1.5.0.dist-info/METADATA
pytest_coverage_impact-1.5.0.dist-info/WHEEL
pytest_coverage_impact-1.5.0.dist-info/entry_points.txt
pytest_coverage_impact-1.5.0.dist-info/top_level.txt
pytest_coverage_impact-1.5.0.dist-info/RECORD
